COPYING
MANIFEST.in
README.rst
requirements-install.txt
requirements.txt
setup.py
tasks.py
lino_shop/__init__.py
lino_shop/setup_info.py
lino_shop.egg-info/PKG-INFO
lino_shop.egg-info/SOURCES.txt
lino_shop.egg-info/dependency_links.txt
lino_shop.egg-info/requires.txt
lino_shop.egg-info/top_level.txt
lino_shop/lib/__init__.py
lino_shop/lib/products/__init__.py
lino_shop/lib/products/models.py
lino_shop/lib/products/config/products/Product/full_page.html
lino_shop/lib/products/config/products/Product/item.pub.html
lino_shop/lib/products/config/products/Product/page.pub.html
lino_shop/lib/products/fixtures/__init__.py
lino_shop/lib/products/fixtures/demo.py
lino_shop/lib/shop/__init__.py
lino_shop/lib/shop/help_texts.py
lino_shop/lib/shop/models.py
lino_shop/lib/shop/settings.py
lino_shop/lib/shop/user_types.py
lino_shop/lib/shop/workflows.py
lino_shop/lib/shop/fixtures/__init__.py
lino_shop/lib/shop/fixtures/demo.py
lino_shop/lib/shop/locale/de/LC_MESSAGES/django.mo
lino_shop/lib/shop/locale/de/LC_MESSAGES/django.po
lino_shop/lib/shop/locale/et/LC_MESSAGES/django.po
lino_shop/lib/shop/locale/fr/LC_MESSAGES/django.po
lino_shop/projects/__init__.py
lino_shop/projects/shop1/__init__.py
lino_shop/projects/shop1/manage.py
lino_shop/projects/shop1/settings.py
lino_shop/projects/shop1/media/cache/help/about.About.html
lino_shop/projects/shop1/media/cache/help/about.DateFormats.html
lino_shop/projects/shop1/media/cache/help/about.SiteSearch.html
lino_shop/projects/shop1/media/cache/help/about.TimeZones.html
lino_shop/projects/shop1/media/cache/help/about.html
lino_shop/projects/shop1/media/cache/help/albums.Album.html
lino_shop/projects/shop1/media/cache/help/albums.Albums.html
lino_shop/projects/shop1/media/cache/help/albums.AlbumsByAlbum.html
lino_shop/projects/shop1/media/cache/help/albums.AllFiles.html
lino_shop/projects/shop1/media/cache/help/albums.File.html
lino_shop/projects/shop1/media/cache/help/albums.FileUsage.html
lino_shop/projects/shop1/media/cache/help/albums.FileUsages.html
lino_shop/projects/shop1/media/cache/help/albums.Files.html
lino_shop/projects/shop1/media/cache/help/albums.FilesByAlbum.html
